README.rst
setup.py
cloudify/__init__.py
cloudify/amqp_client.py
cloudify/amqp_client_utils.py
cloudify/broker_config.py
cloudify/cluster.py
cloudify/conflict_handlers.py
cloudify/constants.py
cloudify/context.py
cloudify/decorators.py
cloudify/dispatch.py
cloudify/endpoint.py
cloudify/event.py
cloudify/exceptions.py
cloudify/logs.py
cloudify/lru_cache.py
cloudify/manager.py
cloudify/mocks.py
cloudify/state.py
cloudify/utils.py
cloudify/celery/__init__.py
cloudify/celery/app.py
cloudify/celery/gate_keeper.py
cloudify/celery/logging_server.py
cloudify/compute/__init__.py
cloudify/ctx_wrappers/__init__.py
cloudify/ctx_wrappers/ctx-py.py
cloudify/plugins/__init__.py
cloudify/plugins/lifecycle.py
cloudify/plugins/workflows.py
cloudify/proxy/__init__.py
cloudify/proxy/client.py
cloudify/proxy/server.py
cloudify/test_utils/__init__.py
cloudify/test_utils/dispatch_helper.py
cloudify/test_utils/local_workflow_decorator.py
cloudify/workflows/__init__.py
cloudify/workflows/events.py
cloudify/workflows/local.py
cloudify/workflows/tasks.py
cloudify/workflows/tasks_graph.py
cloudify/workflows/workflow_api.py
cloudify/workflows/workflow_context.py
cloudify_plugins_common.egg-info/PKG-INFO
cloudify_plugins_common.egg-info/SOURCES.txt
cloudify_plugins_common.egg-info/dependency_links.txt
cloudify_plugins_common.egg-info/entry_points.txt
cloudify_plugins_common.egg-info/not-zip-safe
cloudify_plugins_common.egg-info/requires.txt
cloudify_plugins_common.egg-info/top_level.txt
ctx_wrappers/ctx-sh